wordle/__init__.py
wordle/cli.py
wordle/defaults.py
wordle/evaluate.py
wordle/solver.py
wordle/vocab.py
wordle/wordle.py
wordle/data/coverage.json
wordle/data/evaluation.json
wordle/data/index.json
wordle/data/vocabulary.json
wordle/data/vocabulary.txt
python_wordle-0.1.4.dist-info/AUTHORS.rst
python_wordle-0.1.4.dist-info/LICENSE
python_wordle-0.1.4.dist-info/METADATA
python_wordle-0.1.4.dist-info/WHEEL
python_wordle-0.1.4.dist-info/entry_points.txt
python_wordle-0.1.4.dist-info/top_level.txt
python_wordle-0.1.4.dist-info/RECORD
