Metadata-Version: 2.1
Name: python-wordle
Version: 0.1.4
Summary: Wordle -- Game, Solver and Helper!
Home-page: https://github.com/hrishikeshrt/python-wordle
Author: Hrishikesh Terdalkar
Author-email: hrishikeshrt@linuxmail.org
License: MIT license
Keywords: python-wordle,wordle,wordle-solver,wordle-helper,wordle-game
Platform: UNKNOWN
Classifier: Development Status :: 4 - Beta
Classifier: Intended Audience :: Developers
Classifier: License :: OSI Approved :: MIT License
Classifier: Natural Language :: English
Classifier: Programming Language :: Python :: 3
Classifier: Programming Language :: Python :: 3.6
Classifier: Programming Language :: Python :: 3.7
Classifier: Programming Language :: Python :: 3.8
Requires-Python: >=3.6
License-File: LICENSE
License-File: AUTHORS.rst
Requires-Dist: networkx (>=2.5)
Requires-Dist: numpy (>=1.19.5)
Requires-Dist: rich (>=11.2.0)
Requires-Dist: tqdm (>=4.48.2)
